DLRN-0.26.1.data/data/share/dlrn/scripts/api.py
DLRN-0.26.1.data/data/share/dlrn/scripts/bisect.sh
DLRN-0.26.1.data/data/share/dlrn/scripts/build_srpm.sh
DLRN-0.26.1.data/data/share/dlrn/scripts/centos-stream-9.cfg
DLRN-0.26.1.data/data/share/dlrn/scripts/centos.cfg
DLRN-0.26.1.data/data/share/dlrn/scripts/centos8-stream.cfg
DLRN-0.26.1.data/data/share/dlrn/scripts/centos8.cfg
DLRN-0.26.1.data/data/share/dlrn/scripts/centos9-stream.cfg
DLRN-0.26.1.data/data/share/dlrn/scripts/centos9.cfg
DLRN-0.26.1.data/data/share/dlrn/scripts/common-functions
DLRN-0.26.1.data/data/share/dlrn/scripts/db_migrate.py
DLRN-0.26.1.data/data/share/dlrn/scripts/fedora.cfg
DLRN-0.26.1.data/data/share/dlrn/scripts/get_rdo_review.py
DLRN-0.26.1.data/data/share/dlrn/scripts/recreate-promotion-symlinks.py
DLRN-0.26.1.data/data/share/dlrn/scripts/redhat.cfg
DLRN-0.26.1.data/data/share/dlrn/scripts/run_sh_tests.sh
DLRN-0.26.1.data/data/share/dlrn/scripts/run_tests.sh
DLRN-0.26.1.data/data/share/dlrn/scripts/submit_review.sh
dlrn/__init__.py
dlrn/build.py
dlrn/config.py
dlrn/db.py
dlrn/notifications.py
dlrn/purge.py
dlrn/remote.py
dlrn/reporting.py
dlrn/repositories.py
dlrn/rpmspecfile.py
dlrn/rsync.py
dlrn/shell.py
dlrn/user.py
dlrn/utils.py
dlrn/version.py
dlrn/api/__init__.py
dlrn/api/api_logging.py
dlrn/api/config.py
dlrn/api/dlrn_api.py
dlrn/api/graphql.py
dlrn/api/prom_metrics.py
dlrn/api/utils.py
dlrn/api/static/styles.css
dlrn/api/static/utils.js
dlrn/api/templates/report.j2
dlrn/api/templates/votes.j2
dlrn/api/templates/votes_agg.j2
dlrn/api/templates/votes_general.j2
dlrn/api/templates/votes_general_agg.j2
dlrn/drivers/__init__.py
dlrn/drivers/buildrpm.py
dlrn/drivers/coprdriver.py
dlrn/drivers/downstream.py
dlrn/drivers/gitrepo.py
dlrn/drivers/kojidriver.py
dlrn/drivers/local.py
dlrn/drivers/mockdriver.py
dlrn/drivers/pkginfo.py
dlrn/drivers/rdoinfo.py
dlrn/migrations/README
dlrn/migrations/env.py
dlrn/migrations/script.py.mako
DLRN-0.26.1.dist-info/AUTHORS
DLRN-0.26.1.dist-info/LICENSE
DLRN-0.26.1.dist-info/METADATA
DLRN-0.26.1.dist-info/WHEEL
DLRN-0.26.1.dist-info/entry_points.txt
DLRN-0.26.1.dist-info/pbr.json
DLRN-0.26.1.dist-info/top_level.txt
DLRN-0.26.1.dist-info/RECORD
