Metadata-Version: 2.1
Name: DLRN
Version: 0.26.1
Summary: Build packages
Home-page: http://www.openstack.org/
Author: OpenStack
Author-email: openstack-dev@lists.openstack.org
Classifier: Environment :: OpenStack
Classifier: Intended Audience :: Information Technology
Classifier: Intended Audience :: System Administrators
Classifier: License :: OSI Approved :: Apache Software License
Classifier: Operating System :: POSIX :: Linux
Classifier: Programming Language :: Python
Classifier: Programming Language :: Python :: 2
Classifier: Programming Language :: Python :: 2.7
Classifier: Programming Language :: Python :: 2.6
Classifier: Programming Language :: Python :: 3
Classifier: Programming Language :: Python :: 3.3
License-File: LICENSE
Requires-Dist: pbr (>=0.5.6)
Requires-Dist: Jinja2
Requires-Dist: sh (<2.0.0)
Requires-Dist: six
Requires-Dist: PyMySQL (!=1.0.0)
Requires-Dist: PyYAML
Requires-Dist: distroinfo
Requires-Dist: alembic (!=1.4.2,>=0.7.0)
Requires-Dist: pymod2pkg (>=0.5.5)
Requires-Dist: requests
Requires-Dist: Flask
Requires-Dist: passlib (>=1.7.0)
Requires-Dist: graphene (<3.0)
Requires-Dist: graphene-sqlalchemy (>=2.0)
Requires-Dist: flask-sqlalchemy
Requires-Dist: flask-graphql
Requires-Dist: prometheus-client
Requires-Dist: rdopkg (<1.5.0,>=0.45.0) ; (python_version<'3.3')
Requires-Dist: SQLAlchemy (<1.4.0) ; (python_version=='2.7')
Requires-Dist: renderspec (<2.0.0) ; (python_version=='2.7')
Requires-Dist: Flask-HTTPAuth (<4.4.0) ; (python_version=='2.7')
Requires-Dist: pyOpenSSL (<22.0.0) ; (python_version=='2.7')
Requires-Dist: rdopkg (>=0.45.0) ; (python_version>'3.3')
Requires-Dist: SQLAlchemy ; (python_version>='3.3')
Requires-Dist: renderspec ; (python_version>='3.3')
Requires-Dist: Flask-HTTPAuth ; (python_version>='3.3')
